README.md
setup.py
codonw/__init__.py
codonw/codonwlib/codonw.c
codonw/codonwlib/src/codon_all.c
codonw/codonwlib/src/codon_blk.c
codonw/codonwlib/src/codon_idx.c
codonw/codonwlib/src/defaults.c
codonw_slim.egg-info/PKG-INFO
codonw_slim.egg-info/SOURCES.txt
codonw_slim.egg-info/dependency_links.txt
codonw_slim.egg-info/requires.txt
codonw_slim.egg-info/top_level.txt
test/test_regression.py