Metadata-Version: 2.1
Name: codonw-slim
Version: 1.5.0.post1
Summary: UNKNOWN
Home-page: https://github.com/smsaladi/codonw-slim
Author: Shyam Saladi
Author-email: saladi@caltech.edu
License: GPLv2
Platform: UNKNOWN
